ThermoSim/__init__.py
ThermoSim/main.py
thermosim-2.3.5.dist-info/licenses/LICENSE.py
thermosim-2.3.5.dist-info/METADATA
thermosim-2.3.5.dist-info/WHEEL
thermosim-2.3.5.dist-info/top_level.txt
thermosim-2.3.5.dist-info/RECORD
