Metadata-Version: 2.4
Name: ThermoSim
Version: 2.3.5
Summary: A simulation package for thermodynamic systems
Home-page: https://github.com/Nouman090/ThermoSim
Author: Md. Waheduzzaman Basunia Nouman
License: MIT
Project-URL: Bug Tracker, https://github.com/Nouman090/ThermoSim/issues
Project-URL: Source, https://github.com/Nouman090/ThermoSim
Project-URL: Wiki, https://github.com/Nouman090/ThermoSim/wiki
License-File: LICENSE.py
Requires-Dist: numpy
Requires-Dist: scipy
Requires-Dist: matplotlib
Requires-Dist: CoolProp
Requires-Dist: pandas
Requires-Dist: CoolProp
Requires-Dist: pymoo
Dynamic: author
Dynamic: description
Dynamic: description-content-type
Dynamic: home-page
Dynamic: license
Dynamic: license-file
Dynamic: project-url
Dynamic: requires-dist
Dynamic: summary
